pyroll20/__init__.py
pyroll20/pyroll20.py
pyroll20-0.1.9.dist-info/LICENSE
pyroll20-0.1.9.dist-info/METADATA
pyroll20-0.1.9.dist-info/WHEEL
pyroll20-0.1.9.dist-info/top_level.txt
pyroll20-0.1.9.dist-info/RECORD
