Metadata-Version: 2.1
Name: pyroll20
Version: 0.1.9
Summary: A light, Roll20 syntax compatible, python dice roller
Home-page: https://github.com/NoPantsCrash/pydice
Author: george
Author-email: abtziangiorgos@gmail.com
License: GNU GENERAL PUBLIC LICENSE v3
Platform: UNKNOWN
